pygeclip/__init__.py
pygeclip-0.0.1.dist-info/METADATA
pygeclip-0.0.1.dist-info/WHEEL
pygeclip-0.0.1.dist-info/top_level.txt
pygeclip-0.0.1.dist-info/RECORD
