Metadata-Version: 2.1
Name: pygeclip
Version: 0.0.1
Summary: A small package which helps in easy integeration with PageClip API
Home-page: https://github.com/SakshamSingh-v2/Pygeclip
Author: Saksham Singh
Author-email: sakshamkaundal01@gmail.com
License: UNKNOWN
Platform: UNKNOWN
Classifier: Programming Language :: Python :: 3
Classifier: License :: OSI Approved :: MIT License
Classifier: Operating System :: OS Independent
Requires-Python: >=3.6
